DatabaseCatlogUtility/DatabaseAmazonRedshift.py
DatabaseCatlogUtility/DatabaseDremio.py
DatabaseCatlogUtility/DatabaseGoogleBigQuery.py
DatabaseCatlogUtility/DatabaseInMemory.py
DatabaseCatlogUtility/DatabaseMSSQLServer.py
DatabaseCatlogUtility/DatabaseMySql.py
DatabaseCatlogUtility/DatabaseOracle.py
DatabaseCatlogUtility/DatabasePostgress.py
DatabaseCatlogUtility/DatabaseSAPHANA.py
DatabaseCatlogUtility/DatabaseSnowFlake.py
DatabaseCatlogUtility/Databasecatlog.py
DatabaseCatlogUtility/__init__.py
databasecatlogutility-0.0.12.dist-info/LICENCE.txt
databasecatlogutility-0.0.12.dist-info/METADATA
databasecatlogutility-0.0.12.dist-info/WHEEL
databasecatlogutility-0.0.12.dist-info/top_level.txt
databasecatlogutility-0.0.12.dist-info/RECORD
